HSL/hsl.cp310-win_amd64.pyd
HSL/testing.cp310-win_amd64.pyd
HSL-1.0.3.data/data/lib/site-packages/HSL/LICENSE
HSL-1.0.3.data/data/lib/site-packages/HSL/MANIFEST.in
HSL-1.0.3.data/data/lib/site-packages/HSL/__init__.pxd
HSL-1.0.3.data/data/lib/site-packages/HSL/__init__.py
HSL-1.0.3.data/data/lib/site-packages/HSL/example.py
HSL-1.0.3.data/data/lib/site-packages/HSL/hsl.pxd
HSL-1.0.3.data/data/lib/site-packages/HSL/hsl.pyx
HSL-1.0.3.data/data/lib/site-packages/HSL/hsl_c.c
HSL-1.0.3.data/data/lib/site-packages/HSL/pyproject.toml
HSL-1.0.3.data/data/lib/site-packages/HSL/requirements.txt
HSL-1.0.3.data/data/lib/site-packages/HSL/setup_hsl.py
HSL-1.0.3.data/data/lib/site-packages/HSL/testing.pyx
HSL-1.0.3.data/data/lib/site-packages/HSL/test/HSL_testing.py
HSL-1.0.3.dist-info/LICENSE
HSL-1.0.3.dist-info/METADATA
HSL-1.0.3.dist-info/WHEEL
HSL-1.0.3.dist-info/top_level.txt
HSL-1.0.3.dist-info/RECORD
