Metadata-Version: 2.1
Name: HSL
Version: 1.0.3
Summary: HSL conversion tools
Home-page: https://github.com/yoyoberenguer/HSL
Author: Yoann Berenguer
Author-email: yoyoberenguer@hotmail.com
License: MIT
Project-URL: Bug Reports, https://github.com/yoyoberenguer/HSL/issues
Project-URL: Source, https://github.com/yoyoberenguer/HSL
Platform: any
Classifier: Development Status :: 4 - Beta
Classifier: Intended Audience :: Developers
Classifier: Topic :: Software Development :: Build Tools
Classifier: Operating System :: Microsoft :: Windows
Classifier: Programming Language :: Python
Classifier: Programming Language :: Cython
Classifier: Programming Language :: C
Classifier: License :: OSI Approved :: MIT License
Classifier: Programming Language :: Python :: 3.6
Classifier: Programming Language :: Python :: 3.7
Classifier: Programming Language :: Python :: 3.8
Classifier: Programming Language :: Python :: 3.9
Classifier: Programming Language :: Python :: 3.10
Requires-Python: >=3.0
Requires-Dist: setuptools (>=49.2.1)
Requires-Dist: Cython (>=0.28)
